{
  "formatVersion": "1.1",
  "component": {
    "group": "io.github.peavers",
    "module": "utils",
    "version": "1.0-SNAPSHOT",
    "attributes": {
      "org.gradle.status": "integration"
    }
  },
  "createdBy": {
    "gradle": {
      "version": "7.5.1"
    }
  },
  "variants": [
    {
      "name": "apiElements",
      "attributes": {
        "org.gradle.category": "library",
        "org.gradle.dependency.bundling": "external",
        "org.gradle.jvm.version": 17,
        "org.gradle.libraryelements": "jar",
        "org.gradle.usage": "java-api"
      },
      "files": [
        {
          "name": "utils-1.0-SNAPSHOT.jar",
          "url": "utils-1.0-SNAPSHOT.jar",
          "size": 3056,
          "sha512": "c314ba7ff46adfb8fa45e319e2c36e12b6767c1035317bfc558a31d5e7f6455e40fa4872af5f267e293915a87bcebf036c7001891264281e0980a0422d6fed94",
          "sha256": "ba91af05e1cc5baa6ea1547c2ed05c486bff8cb1646ff94ceb24b653139562c5",
          "sha1": "23580f1f275e13fa93e8ac1662431d8154f2ad3b",
          "md5": "275836b458a9305433707b8ec61882ff"
        }
      ]
    },
    {
      "name": "runtimeElements",
      "attributes": {
        "org.gradle.category": "library",
        "org.gradle.dependency.bundling": "external",
        "org.gradle.jvm.version": 17,
        "org.gradle.libraryelements": "jar",
        "org.gradle.usage": "java-runtime"
      },
      "dependencies": [
        {
          "group": "io.github.resilience4j",
          "module": "resilience4j-all",
          "version": {
            "requires": "2.0.2"
          }
        },
        {
          "group": "org.apache.commons",
          "module": "commons-text",
          "version": {
            "requires": "1.10.0"
          }
        },
        {
          "group": "org.apache.commons",
          "module": "commons-collections4",
          "version": {
            "requires": "4.4"
          }
        },
        {
          "group": "commons-io",
          "module": "commons-io",
          "version": {
            "requires": "2.11.0"
          }
        },
        {
          "group": "org.slf4j",
          "module": "slf4j-api",
          "version": {
            "requires": "2.0.6"
          }
        }
      ],
      "files": [
        {
          "name": "utils-1.0-SNAPSHOT.jar",
          "url": "utils-1.0-SNAPSHOT.jar",
          "size": 3056,
          "sha512": "c314ba7ff46adfb8fa45e319e2c36e12b6767c1035317bfc558a31d5e7f6455e40fa4872af5f267e293915a87bcebf036c7001891264281e0980a0422d6fed94",
          "sha256": "ba91af05e1cc5baa6ea1547c2ed05c486bff8cb1646ff94ceb24b653139562c5",
          "sha1": "23580f1f275e13fa93e8ac1662431d8154f2ad3b",
          "md5": "275836b458a9305433707b8ec61882ff"
        }
      ]
    }
  ]
}
